{ "compressionlevel":-1,
 "height":60,
 "infinite":false,
 "layers":[
        {
         "compression":"zlib",
         "data":"eJzt0cEJADAIBEF7SMXp3BbiQzQwC\/cfuAhJr90zu9980x6+Xt82Lx8fHx8fHx8fHx8fHx8fHx8fHx8fHx8fHx9fxTvt2e7b\/i9fr0+1EswM4D4=",
         "encoding":"base64",
         "height":60,
         "id":5,
         "name":"static-collision",
         "opacity":1,
         "type":"tilelayer",
         "visible":true,
         "width":40,
         "x":0,
         "y":0
        }, 
        {
         "compression":"zlib",
         "data":"eJzt0rENgEAIQFE6R1EX0P030\/oatILT9xM6ipdAhKSnrUvEVjhZx71zFs7Y6N+b+SotX\/B1s2bx8fHx8fHx8fHx8fHx8fHx8fHx8fHx8fHx\/cuXeas9M\/g637f7\/83u07suSZid+A==",
         "encoding":"base64",
         "height":60,
         "id":1,
         "name":"floors",
         "opacity":1,
         "type":"tilelayer",
         "visible":true,
         "width":40,
         "x":0,
         "y":0
        }, 
        {
         "compression":"zlib",
         "data":"eJzt2bENwjAQheGbhYYdAMEOgGAHEDAEiLlxeXaEKV50PqT\/l16R7oujVDajuVqUbQZv2fGtym6Dt+v49mXHwTs3Jn+2h449qm3z7O3XeM6k1pctfFqt7+V2iedM6p3fOkzxPXxa+LTwaeHTwqeFTwufFj4tfFr4tPBp4dPCp4VPC58WPi18Wvi08Gll952svrP0ZfDdrb6z9GXw9cL3u4fVd4K+DL7s\/+8\/+55Wf\/sRe8\/1okF9AMAcUd0=",
         "encoding":"base64",
         "height":60,
         "id":2,
         "name":"walls",
         "opacity":1,
         "type":"tilelayer",
         "visible":true,
         "width":40,
         "x":0,
         "y":0
        }, 
        {
         "compression":"zlib",
         "data":"eJztzkERAAAEADAZ9O+hnga+nNsSLAIAAAAAAAAA4K\/K7cHs+g+YNY0eAZM=",
         "encoding":"base64",
         "height":60,
         "id":4,
         "name":"props",
         "opacity":1,
         "type":"tilelayer",
         "visible":true,
         "width":40,
         "x":0,
         "y":0
        }, 
        {
         "draworder":"topdown",
         "id":3,
         "name":"entities",
         "objects":[
                {
                 "height":32,
                 "id":1,
                 "name":"",
                 "properties":[
                        {
                         "name":"target-dest-coords-x",
                         "type":"int",
                         "value":17
                        }, 
                        {
                         "name":"target-dest-coords-y",
                         "type":"int",
                         "value":10
                        }, 
                        {
                         "name":"target-level",
                         "type":"string",
                         "value":"level-breakroom-initial"
                        }],
                 "rotation":0,
                 "type":"teleporter",
                 "visible":true,
                 "width":32,
                 "x":1248,
                 "y":1664
                }, 
                {
                 "height":32,
                 "id":5,
                 "name":"",
                 "properties":[
                        {
                         "name":"target-dest-coords-x",
                         "type":"int",
                         "value":17
                        }, 
                        {
                         "name":"target-dest-coords-y",
                         "type":"int",
                         "value":10
                        }, 
                        {
                         "name":"target-level",
                         "type":"string",
                         "value":"level-breakroom-initial"
                        }],
                 "rotation":0,
                 "type":"teleporter",
                 "visible":true,
                 "width":32,
                 "x":1248,
                 "y":1696
                }],
         "opacity":1,
         "type":"objectgroup",
         "visible":true,
         "x":0,
         "y":0
        }],
 "nextlayerid":6,
 "nextobjectid":6,
 "orientation":"orthogonal",
 "renderorder":"right-down",
 "tiledversion":"1.10.2",
 "tileheight":32,
 "tilesets":[
        {
         "firstgid":1,
         "source":"..\/.tsx\/mi-rb-walls-3d.tsx"
        }, 
        {
         "firstgid":1321,
         "source":"..\/.tsx\/mi-rb-floors.tsx"
        }, 
        {
         "firstgid":1921,
         "source":"..\/.tsx\/omori-black-space.tsx"
        }, 
        {
         "firstgid":4993,
         "source":"..\/.tsx\/collision.tsx"
        }],
 "tilewidth":32,
 "type":"map",
 "version":"1.10",
 "width":40
}